workflows_acp/__init__.py
workflows_acp/_templating.py
workflows_acp/acp_wrapper.py
workflows_acp/cli.py
workflows_acp/constants.py
workflows_acp/events.py
workflows_acp/llm_wrapper.py
workflows_acp/llms/__init__.py
workflows_acp/llms/anthropic_llm.py
workflows_acp/llms/google_llm.py
workflows_acp/llms/models.py
workflows_acp/llms/openai_llm.py
workflows_acp/llms/retry.py
workflows_acp/mcp_wrapper.py
workflows_acp/models.py
workflows_acp/tools/__init__.py
workflows_acp/tools/agentfs.py
workflows_acp/tools/bash.py
workflows_acp/tools/definitions.py
workflows_acp/tools/filesystem.py
workflows_acp/tools/memory.py
workflows_acp/tools/todo.py
workflows_acp/workflow.py
workflows_acp-0.4.0a0.dist-info/WHEEL
workflows_acp-0.4.0a0.dist-info/entry_points.txt
workflows_acp-0.4.0a0.dist-info/METADATA
workflows_acp-0.4.0a0.dist-info/RECORD
