Metadata-Version: 2.3
Name: workflows-acp
Version: 0.4.0a0
Summary: LlamaIndex Agent Workflows over the ACP wire
Requires-Dist: agent-client-protocol>=0.7.1
Requires-Dist: agentfs-sdk>=0.4.1
Requires-Dist: anthropic>=0.75.0
Requires-Dist: google-genai>=1.56.0
Requires-Dist: llama-index-workflows>=2.11.6
Requires-Dist: mcp-use>=1.5.1
Requires-Dist: openai>=2.14.0
Requires-Dist: psutil>=7.2.1
Requires-Dist: pyyaml>=6.0.3
Requires-Dist: typer>=0.21.0
Requires-Python: >=3.11
